icotools/__init__.py
icotools/__main__.py
icotools/balancer.py
icotools/guesser.py
icotools/templates/guesses_exitques.html
icotools/templates/guesses_instructions_mp3.html
icotools/templates/guesses_instructions_mp4.html
icotools/templates/guesses_mp3.html
icotools/templates/guesses_mp4.html
icotools/templates/php_temp.php
iconicitymeasures-0.0.4.dist-info/METADATA
iconicitymeasures-0.0.4.dist-info/WHEEL
iconicitymeasures-0.0.4.dist-info/top_level.txt
iconicitymeasures-0.0.4.dist-info/RECORD
