Metadata-Version: 2.1
Name: iconicitymeasures
Version: 0.0.4
Summary: Tools for collecting behavioural measures of iconicity
Home-page: UNKNOWN
Author: Bonnie McLean
Author-email: <59.b.mclean@gmail.com>
License: UNKNOWN
Keywords: python,iconicity
Platform: UNKNOWN
Classifier: Development Status :: 3 - Alpha
Classifier: Intended Audience :: Education
Classifier: Programming Language :: Python :: 3
Classifier: Operating System :: MacOS :: MacOS X
Classifier: Operating System :: Microsoft :: Windows
